silver_spectacle/__init__.py
silver_spectacle/image_converters.py
silver_spectacle/library.py
silver_spectacle/png.py
silver_spectacle/server.py
silver_spectacle-0.8.0.dist-info/METADATA
silver_spectacle-0.8.0.dist-info/WHEEL
silver_spectacle-0.8.0.dist-info/top_level.txt
silver_spectacle-0.8.0.dist-info/RECORD
