Metadata-Version: 2.1
Name: silver-spectacle
Version: 0.8.0
Summary: An easier way to display data
Home-page: https://github.com/jeff-hykin/silver_spectacle.git
Author: Jeff Hykin
Author-email: jeff.hykin@gmail.com
License: MIT
Platform: UNKNOWN
Requires-Python: >=3.6
Requires-Dist: aiohttp (>=3.7.4)
Requires-Dist: python-socketio (>=5.3.0)
Requires-Dist: requests (>=2.26.0)
